pummel/__init__.py
pummel/classes.py
pummel/constants.py
pummel-0.15.0.data/scripts/pummel
pummel-0.15.0.dist-info/LICENSE
pummel-0.15.0.dist-info/METADATA
pummel-0.15.0.dist-info/WHEEL
pummel-0.15.0.dist-info/top_level.txt
pummel-0.15.0.dist-info/RECORD
